chart_me/__init__.py
chart_me/__main__.py
chart_me/chart_configs.py
chart_me/chart_me_logic.py
chart_me/data_validation_strategy.py
chart_me/datatype_infer_strategy.py
chart_me/errors.py
chart_me/pandas_util.py
chart_me/charting_assembly_strategy/__init__.py
chart_me/charting_assembly_strategy/bivariate.py
chart_me/charting_assembly_strategy/univariate.py
chart_me-0.2.0.dist-info/entry_points.txt
chart_me-0.2.0.dist-info/LICENSE
chart_me-0.2.0.dist-info/WHEEL
chart_me-0.2.0.dist-info/METADATA
chart_me-0.2.0.dist-info/RECORD
