Metadata-Version: 2.1
Name: chart_me
Version: 0.2.0
Summary: Charting that keeps you in the EDA flow
Author-email: Luke Garzia <garzia.luke@gmail.com>
Requires-Python: >=3.10
Classifier: License :: OSI Approved :: MIT License
Requires-Dist: pandas
Requires-Dist: altair
Requires-Dist: typing-extensions
Requires-Dist: typer
Requires-Dist: sphinx ; extra == "doc"
Requires-Dist: myst-nb ; extra == "doc"
Requires-Dist: sphinx-rtd-theme ; extra == "doc"
Requires-Dist: sphinx-autoapi ; extra == "doc"
Requires-Dist: pytest ; extra == "test"
Requires-Dist: vega_datasets ; extra == "test"
Requires-Dist: notebook ; extra == "test"
Requires-Dist: pre-commit ; extra == "test"
Requires-Dist: interrogate ; extra == "test"
Requires-Dist: pytest-cov ; extra == "test"
Requires-Dist: tox ; extra == "test"
Requires-Dist: mypy ; extra == "test"
Requires-Dist: black ; extra == "test"
Requires-Dist: flake8 ; extra == "test"
Requires-Dist: isort ; extra == "test"
Requires-Dist: bump2version ; extra == "test"
Requires-Dist: flake8-comprehensions ; extra == "test"
Requires-Dist: types-python-dateutil ; extra == "test"
Project-URL: Home, https://github.com/lgarzia/chart_me
Provides-Extra: doc
Provides-Extra: test
